TMEImmune/ISTME.py
TMEImmune/SIAscore.py
TMEImmune/TME_score.py
TMEImmune/__init__.py
TMEImmune/data_processing.py
TMEImmune/estimateScore.py
TMEImmune/nb_utilities.py
TMEImmune/netbio.py
TMEImmune/optimal.py
TMEImmune/data/c2.all.v7.2.symbols.gmt
TMEImmune/data/gene_sets_full.json
TMEImmune/data/Gide/expression_mRNA.norm3.txt
TMEImmune/data/Gide/pathway_expression_ssgsea.txt
TMEImmune/data/Gide/patient_df.txt
TMEImmune/data/nb_biomarker/CTLA4.txt
TMEImmune/data/nb_biomarker/PD-L1.txt
TMEImmune/data/nb_biomarker/PD1.txt
TMEImmune/data/nb_biomarker/PD1_CTLA4.txt
TMEImmune/data/nb_biomarker/PD1_PD-L1_CTLA4.txt
TMEImmune/data/nb_biomarker/README.txt
tmeimmune-1.3.3.dist-info/licenses/LICENSE
tmeimmune-1.3.3.dist-info/METADATA
tmeimmune-1.3.3.dist-info/WHEEL
tmeimmune-1.3.3.dist-info/top_level.txt
tmeimmune-1.3.3.dist-info/RECORD
