Metadata-Version: 2.4
Name: TMEImmune
Version: 1.3.3
Summary: Python package for calculating TME scores
Home-page: https://github.com/ShahriyariLab/TMEImmune
Author: Qilu Zhou
Author-email: <qiluzhou@umass.edu>
Keywords: python,TME score
Classifier: Development Status :: 3 - Alpha
Classifier: Intended Audience :: Education
Classifier: Programming Language :: Python :: 3
Classifier: Operating System :: MacOS :: MacOS X
Classifier: Operating System :: Microsoft :: Windows
Requires-Python: >=3.10
License-File: LICENSE
Requires-Dist: pandas>=1.5.0
Requires-Dist: numpy>=1.23.5
Requires-Dist: rnanorm
Requires-Dist: inmoose
Requires-Dist: lifelines
Requires-Dist: scikit-learn
Requires-Dist: matplotlib
Requires-Dist: scipy
Requires-Dist: statsmodels
Requires-Dist: joblib
Dynamic: author
Dynamic: author-email
Dynamic: classifier
Dynamic: description
Dynamic: description-content-type
Dynamic: home-page
Dynamic: keywords
Dynamic: license-file
Dynamic: requires-dist
Dynamic: requires-python
Dynamic: summary
